odoo8_addon_report_xls-8.0.0.6.1.99.dev12-py2.7-nspkg.pth
odoo8_addon_report_xls-8.0.0.6.1.99.dev12.dist-info/DESCRIPTION.rst
odoo8_addon_report_xls-8.0.0.6.1.99.dev12.dist-info/METADATA
odoo8_addon_report_xls-8.0.0.6.1.99.dev12.dist-info/RECORD
odoo8_addon_report_xls-8.0.0.6.1.99.dev12.dist-info/WHEEL
odoo8_addon_report_xls-8.0.0.6.1.99.dev12.dist-info/metadata.json
odoo8_addon_report_xls-8.0.0.6.1.99.dev12.dist-info/namespace_packages.txt
odoo8_addon_report_xls-8.0.0.6.1.99.dev12.dist-info/top_level.txt
odoo_addons/report_xls/README.rst
odoo_addons/report_xls/__init__.py
odoo_addons/report_xls/__openerp__.py
odoo_addons/report_xls/ir_report.py
odoo_addons/report_xls/report_xls.py
odoo_addons/report_xls/utils.py
odoo_addons/report_xls/i18n/report_xls.pot
odoo_addons/report_xls/static/description/help.png
odoo_addons/report_xls/static/description/icon.png
odoo_addons/report_xls/static/description/index.html
odoo_addons/report_xls/static/description/open_receivables.png
