Metadata-Version: 2.0
Name: odoo8-addon-report-xls
Version: 8.0.0.6.1.99.dev12
Summary: Excel report engine
Home-page: http://www.noviat.com
Author: Noviat,Odoo Community Association (OCA)
Author-email: support@odoo-community.org
License: AGPL-3
Platform: UNKNOWN
Classifier: Programming Language :: Python
Classifier: Framework :: Odoo
Classifier: License :: OSI Approved :: GNU Affero General Public License v3
Requires-Python: ~=2.7
Requires-Dist: odoo (<9.0a,>=8.0a)
Requires-Dist: xlwt
